dobby/__init__.py
dobby/_logging.py
dobby/executor.py
dobby/py.typed
dobby/common_tools/__init__.py
dobby/common_tools/tavily.py
dobby/exceptions/__init__.py
dobby/exceptions/tool.py
dobby/providers/__init__.py
dobby/providers/_retry.py
dobby/providers/base.py
dobby/providers/anthropic/.gitkeep
dobby/providers/gemini/__init__.py
dobby/providers/gemini/adapter.py
dobby/providers/gemini/converters.py
dobby/providers/openai/__init__.py
dobby/providers/openai/adapter.py
dobby/providers/openai/completions.py
dobby/providers/openai/converters.py
dobby/retriever/__init__.py
dobby/retriever/base.py
dobby/retriever/hybrid_retriever.py
dobby/tools/__init__.py
dobby/tools/base.py
dobby/tools/injected.py
dobby/tools/schema_utils.py
dobby/tools/tool.py
dobby/types/__init__.py
dobby/types/document_part.py
dobby/types/image_part.py
dobby/types/message.py
dobby/types/reasoning_part.py
dobby/types/stream_events.py
dobby/types/text_part.py
dobby/types/tool_events.py
dobby/types/tool_part.py
dobby/types/tool_result_part.py
dobby/types/usage.py
dobby/vector_store/__init__.py
dobby/vector_store/azure_ai_search.py
dobby/vector_store/base.py
dobby_sdk-0.2.7.dist-info/METADATA
dobby_sdk-0.2.7.dist-info/WHEEL
dobby_sdk-0.2.7.dist-info/licenses/LICENSE
dobby_sdk-0.2.7.dist-info/RECORD
